wellarchitecturedesign/__init__.py
wellarchitecturedesign/_version.py
wellarchitecturedesign/elements.py
wellarchitecturedesign/well.py
wellarchitecturedesign-0.1.1.dist-info/LICENSE.md
wellarchitecturedesign-0.1.1.dist-info/METADATA
wellarchitecturedesign-0.1.1.dist-info/WHEEL
wellarchitecturedesign-0.1.1.dist-info/top_level.txt
wellarchitecturedesign-0.1.1.dist-info/RECORD
