Metadata-Version: 2.1
Name: wellarchitecturedesign
Version: 0.1.1
Summary: A package for well architecture design and visualization
License: MIT
Keywords: well,architecture,design,visualization
Classifier: Development Status :: 3 - Alpha
Classifier: Intended Audience :: Science/Research
Classifier: Programming Language :: Python :: 3
Classifier: Programming Language :: Python :: 3.7
Classifier: Programming Language :: Python :: 3.8
Classifier: Programming Language :: Python :: 3.9
Classifier: Programming Language :: Python :: 3.10
Classifier: Programming Language :: Python :: 3.11
Requires-Python: >=3.7
License-File: LICENSE.md
Requires-Dist: numpy>=1.21.0
Requires-Dist: matplotlib>=3.4.0
